Metadata-Version: 1.0
Name: visart
Version: 0.6
Summary: Minimalistic plots for data analisys
Home-page: UNKNOWN
Author: UNKNOWN
Author-email: vlad.zhyvov@gmail.com
License: UNKNOWN
Platform: UNKNOWN
